ringkernel/__init__.py
ringkernel/_ringkernel.abi3.so
ringkernel/_ringkernel.pyi
ringkernel/py.typed
ringkernel-0.4.0.dist-info/METADATA
ringkernel-0.4.0.dist-info/WHEEL
ringkernel-0.4.0.dist-info/RECORD
