Metadata-Version: 2.4
Name: ringkernel
Version: 0.4.0
Classifier: Development Status :: 4 - Beta
Classifier: Intended Audience :: Developers
Classifier: Intended Audience :: Science/Research
Classifier: License :: OSI Approved :: MIT License
Classifier: License :: OSI Approved :: Apache Software License
Classifier: Operating System :: POSIX :: Linux
Classifier: Operating System :: MacOS
Classifier: Operating System :: Microsoft :: Windows
Classifier: Programming Language :: Python :: 3
Classifier: Programming Language :: Python :: 3.8
Classifier: Programming Language :: Python :: 3.9
Classifier: Programming Language :: Python :: 3.10
Classifier: Programming Language :: Python :: 3.11
Classifier: Programming Language :: Python :: 3.12
Classifier: Programming Language :: Rust
Classifier: Topic :: Scientific/Engineering
Classifier: Topic :: System :: Distributed Computing
Classifier: Topic :: System :: Hardware :: Symmetric Multi-processing
Requires-Dist: pytest>=7.0 ; extra == 'dev'
Requires-Dist: pytest-asyncio>=0.21 ; extra == 'dev'
Requires-Dist: hypothesis>=6.0 ; extra == 'dev'
Requires-Dist: mypy>=1.0 ; extra == 'dev'
Requires-Dist: sphinx>=7.0 ; extra == 'docs'
Requires-Dist: sphinx-rtd-theme>=2.0 ; extra == 'docs'
Requires-Dist: myst-parser>=2.0 ; extra == 'docs'
Requires-Dist: numpy>=1.20 ; extra == 'numpy'
Provides-Extra: dev
Provides-Extra: docs
Provides-Extra: numpy
Summary: GPU-native persistent actor model framework
Keywords: gpu,cuda,actor,async,distributed,parallel
Author: RingKernel Contributors
License: MIT OR Apache-2.0
Requires-Python: >=3.8
Project-URL: Documentation, https://ringkernel.readthedocs.io
Project-URL: Homepage, https://github.com/ringkernel/ringkernel
Project-URL: Issues, https://github.com/ringkernel/ringkernel/issues
Project-URL: Repository, https://github.com/ringkernel/ringkernel
